dataprepkit/__init__.py
dataprepkit/helpers.py
dataprepkit/helpers/__init__.py
dataprepkit/helpers/connectors/__init__.py
dataprepkit/helpers/connectors/lakehouse.py
dataprepkit/helpers/connectors/warehouse.py
dataprepkit/helpers/dims/__init__.py
dataprepkit/helpers/dims/dimension_registry.py
dataprepkit/helpers/transforms/__init__.py
dataprepkit/helpers/transforms/insert_update.py
dataprepkit/processors/__init__.py
dataprepkit/processors/dimensions/__init__.py
dataprepkit/processors/dimensions/dim_common.py
dataprepkit/processors/dimensions/dim_company.py
dataprepkit/processors/dimensions/dim_measure.py
dataprepkit/processors/dimensions/dim_region.py
dataprepkit/processors/quarterly/__init__.py
dataprepkit/processors/quarterly/qdata_processor.py
ofwat_dataprepkit-0.9.dist-info/licenses/LICENSE
ofwat_dataprepkit-0.9.dist-info/METADATA
ofwat_dataprepkit-0.9.dist-info/WHEEL
ofwat_dataprepkit-0.9.dist-info/top_level.txt
ofwat_dataprepkit-0.9.dist-info/RECORD
