Metadata-Version: 2.4
Name: ofwat-dataprepkit
Version: 0.9
Summary: ETL Tools for Fabric
Home-page: https://github.com/Ofwat/dataprepkit
Author: Ofwat
Project-URL: Source, https://github.com/Ofwat/dataprepkit
Project-URL: Tracker, https://github.com/Ofwat/dataprepkit/issues
Keywords: fabric etl
License-File: LICENSE
Requires-Dist: pandas
Requires-Dist: numpy
Requires-Dist: sqlalchemy
Requires-Dist: pyodbc
Dynamic: author
Dynamic: description
Dynamic: description-content-type
Dynamic: home-page
Dynamic: keywords
Dynamic: license-file
Dynamic: project-url
Dynamic: requires-dist
Dynamic: summary
